{
	"info": {
		"_postman_id": "134aab4e-e60c-4182-ad64-406fa626e71c",
		"name": "E2E Simple Book API",
		"schema": "https://schema.getpostman.com/json/collection/v2.1.0/collection.json",
		"_exporter_id": "29370892"
	},
	"item": [
		{
			"name": "Status",
			"event": [
				{
					"listen": "test",
					"script": {
						"exec": [
							"pm.test(\"Status code is 200\", function () {\r",
							"    pm.response.to.have.status(200);\r",
							"});\r",
							"\r",
							"const response = pm.response.json();\r",
							"console.log(response.status);\r",
							"pm.test(\"Status OK\",()=>{\r",
							"pm.expect(response.status).to.be.eql(\"OK\");\r",
							"}\r",
							")"
						],
						"type": "text/javascript"
					}
				}
			],
			"request": {
				"method": "GET",
				"header": [],
				"url": {
					"raw": "{{basicURL}}/status",
					"host": [
						"{{basicURL}}"
					],
					"path": [
						"status"
					]
				}
			},
			"response": []
		},
		{
			"name": "List of Books",
			"event": [
				{
					"listen": "test",
					"script": {
						"exec": [
							"pm.test(\"Status code is 200\", function () {\r",
							"    pm.response.to.have.status(200);\r",
							"});\r",
							"\r",
							"const response = pm.response.json();\r",
							"const availableBook = response.filter((book)=>book.available===true);\r",
							"console.log(availableBook);\r",
							"\r",
							"pm.globals.set(\"book_ID\", availableBook[0].id);"
						],
						"type": "text/javascript"
					}
				}
			],
			"request": {
				"method": "GET",
				"header": [],
				"url": {
					"raw": "{{basicURL}}/books?type=fiction&limit=2",
					"host": [
						"{{basicURL}}"
					],
					"path": [
						"books"
					],
					"query": [
						{
							"key": "type",
							"value": "fiction"
						},
						{
							"key": "limit",
							"value": "2"
						}
					]
				}
			},
			"response": []
		},
		{
			"name": "Get a single book",
			"event": [
				{
					"listen": "test",
					"script": {
						"exec": [
							"pm.test(\"Status code is 200\", function () {\r",
							"    pm.response.to.have.status(200);\r",
							"});"
						],
						"type": "text/javascript"
					}
				}
			],
			"request": {
				"method": "GET",
				"header": [],
				"url": {
					"raw": "{{basicURL}}//books/:bookId",
					"host": [
						"{{basicURL}}"
					],
					"path": [
						"",
						"books",
						":bookId"
					],
					"variable": [
						{
							"key": "bookId",
							"value": "{{book_ID}}"
						}
					]
				}
			},
			"response": []
		},
		{
			"name": "Submit an order",
			"event": [
				{
					"listen": "test",
					"script": {
						"exec": [
							"pm.test(\"Status code is 201\", function () {\r",
							"    pm.response.to.have.status(201);\r",
							"});\r",
							"\r",
							"const response=pm.response.json();\r",
							"pm.globals.set(\"order_ID\", response.orderId);"
						],
						"type": "text/javascript"
					}
				}
			],
			"request": {
				"auth": {
					"type": "bearer",
					"bearer": [
						{
							"key": "token",
							"value": "{{accessToken}}",
							"type": "string"
						}
					]
				},
				"method": "POST",
				"header": [],
				"body": {
					"mode": "raw",
					"raw": "{\r\n  \"bookId\": {{book_ID}},\r\n  \"customerName\": \"John\"\r\n}",
					"options": {
						"raw": {
							"language": "json"
						}
					}
				},
				"url": {
					"raw": "{{basicURL}}/orders",
					"host": [
						"{{basicURL}}"
					],
					"path": [
						"orders"
					]
				}
			},
			"response": []
		},
		{
			"name": "Get all orders",
			"event": [
				{
					"listen": "test",
					"script": {
						"exec": [
							"pm.test(\"Status code is 200\", function () {\r",
							"    pm.response.to.have.status(200);\r",
							"});"
						],
						"type": "text/javascript"
					}
				}
			],
			"protocolProfileBehavior": {
				"disableBodyPruning": true
			},
			"request": {
				"auth": {
					"type": "bearer",
					"bearer": [
						{
							"key": "token",
							"value": "984d2728c74a6abf5f86bd77d8357bfa9fde5d7f55986e8d071d4a074ea5e8db",
							"type": "string"
						}
					]
				},
				"method": "GET",
				"header": [],
				"body": {
					"mode": "raw",
					"raw": "{\r\n  \"bookId\": 1,\r\n  \"customerName\": \"John\"\r\n}",
					"options": {
						"raw": {
							"language": "json"
						}
					}
				},
				"url": {
					"raw": "{{basicURL}}/orders",
					"host": [
						"{{basicURL}}"
					],
					"path": [
						"orders"
					]
				}
			},
			"response": []
		},
		{
			"name": "Get an order",
			"event": [
				{
					"listen": "test",
					"script": {
						"exec": [
							"pm.test(\"Status code is 200\", function () {\r",
							"    pm.response.to.have.status(200);\r",
							"});"
						],
						"type": "text/javascript"
					}
				}
			],
			"protocolProfileBehavior": {
				"disableBodyPruning": true
			},
			"request": {
				"auth": {
					"type": "bearer",
					"bearer": [
						{
							"key": "token",
							"value": "984d2728c74a6abf5f86bd77d8357bfa9fde5d7f55986e8d071d4a074ea5e8db",
							"type": "string"
						}
					]
				},
				"method": "GET",
				"header": [],
				"body": {
					"mode": "raw",
					"raw": "{\r\n  \"bookId\": 1,\r\n  \"customerName\": \"John\"\r\n}",
					"options": {
						"raw": {
							"language": "json"
						}
					}
				},
				"url": {
					"raw": "{{basicURL}}/orders/:orderId",
					"host": [
						"{{basicURL}}"
					],
					"path": [
						"orders",
						":orderId"
					],
					"variable": [
						{
							"key": "orderId",
							"value": "{{order_ID}}"
						}
					]
				}
			},
			"response": []
		},
		{
			"name": "Update an order",
			"event": [
				{
					"listen": "test",
					"script": {
						"exec": [
							"pm.test(\"Status code is 204\", function () {\r",
							"    pm.response.to.have.status(204);\r",
							"});"
						],
						"type": "text/javascript"
					}
				}
			],
			"request": {
				"auth": {
					"type": "bearer",
					"bearer": [
						{
							"key": "token",
							"value": "984d2728c74a6abf5f86bd77d8357bfa9fde5d7f55986e8d071d4a074ea5e8db",
							"type": "string"
						}
					]
				},
				"method": "PATCH",
				"header": [],
				"body": {
					"mode": "raw",
					"raw": "{\r\n  \"customerName\": \"John{{$randomLastName}}\"\r\n}",
					"options": {
						"raw": {
							"language": "json"
						}
					}
				},
				"url": {
					"raw": "{{basicURL}}/orders/:orderId",
					"host": [
						"{{basicURL}}"
					],
					"path": [
						"orders",
						":orderId"
					],
					"variable": [
						{
							"key": "orderId",
							"value": "{{order_ID}}"
						}
					]
				}
			},
			"response": []
		},
		{
			"name": "Delete an order",
			"event": [
				{
					"listen": "test",
					"script": {
						"exec": [
							"pm.test(\"Status code is 204\", function () {\r",
							"    pm.response.to.have.status(204);\r",
							"});"
						],
						"type": "text/javascript"
					}
				}
			],
			"request": {
				"auth": {
					"type": "bearer",
					"bearer": [
						{
							"key": "token",
							"value": "984d2728c74a6abf5f86bd77d8357bfa9fde5d7f55986e8d071d4a074ea5e8db",
							"type": "string"
						}
					]
				},
				"method": "DELETE",
				"header": [],
				"body": {
					"mode": "raw",
					"raw": "",
					"options": {
						"raw": {
							"language": "json"
						}
					}
				},
				"url": {
					"raw": "{{basicURL}}/orders/:orderId",
					"host": [
						"{{basicURL}}"
					],
					"path": [
						"orders",
						":orderId"
					],
					"variable": [
						{
							"key": "orderId",
							"value": "{{order_ID}}"
						}
					]
				}
			},
			"response": []
		},
		{
			"name": "API Authentication",
			"request": {
				"method": "POST",
				"header": [],
				"body": {
					"mode": "raw",
					"raw": "{\r\n   \"clientName\": \"Postman\",\r\n   \"clientEmail\": \"gol@example.com\"\r\n}",
					"options": {
						"raw": {
							"language": "json"
						}
					}
				},
				"url": {
					"raw": "{{basicURL}}/api-clients/",
					"host": [
						"{{basicURL}}"
					],
					"path": [
						"api-clients",
						""
					]
				}
			},
			"response": []
		}
	],
	"variable": [
		{
			"key": "basicURL",
			"value": "https://simple-books-api.glitch.me"
		},
		{
			"key": "accessToken",
			"value": "984d2728c74a6abf5f86bd77d8357bfa9fde5d7f55986e8d071d4a074ea5e8db"
		}
	]
}